pclean/__init__.py
pclean/pclean.py
pclean-0.7.dist-info/LICENSE
pclean-0.7.dist-info/METADATA
pclean-0.7.dist-info/WHEEL
pclean-0.7.dist-info/entry_points.txt
pclean-0.7.dist-info/top_level.txt
pclean-0.7.dist-info/RECORD
