Metadata-Version: 2.1
Name: pclean
Version: 0.7
Summary: Find and remove duplicate files in a pCloud account
Home-page: https://bitbucket.org/tipmethewink/pclean
Author: Mark Lee
Author-email: mark@droveend.com
License: UNKNOWN
Keywords: pcloud duplicate
Platform: UNKNOWN
Classifier: Programming Language :: Python :: 3
Classifier: License :: OSI Approved :: GNU General Public License v3 (GPLv3)
Classifier: Operating System :: OS Independent
Requires-Dist: Click
Requires-Dist: pcloud
Requires-Dist: tqdm
